{
    "eggcartons.py": [
        {
            "operation": "DELETE",
            "lines": 0,
            "keyStrokeTimeStamp": "Fri Aug 13 2021 23:10:42",
            "keyStrokeInfo": "",
            "position": "9,2"
        },
        {
            "operation": "DELETE",
            "lines": 0,
            "keyStrokeTimeStamp": "Fri Aug 13 2021 23:10:42",
            "keyStrokeInfo": "",
            "position": "9,1"
        },
        {
            "operation": "DELETE",
            "lines": 1,
            "keyStrokeTimeStamp": "Fri Aug 13 2021 23:10:42",
            "keyStrokeInfo": "",
            "position": "8,23"
        },
        {
            "operation": "TYPED",
            "lines": 0,
            "keyStrokeTimeStamp": "Fri Aug 13 2021 23:10:43",
            "keyStrokeInfo": "\r\n\t",
            "position": "8,23"
        },
        {
            "operation": "TYPED",
            "lines": 0,
            "keyStrokeTimeStamp": "Fri Aug 13 2021 23:10:44",
            "keyStrokeInfo": "e",
            "position": "9,2"
        },
        {
            "operation": "TYPED",
            "lines": 0,
            "keyStrokeTimeStamp": "Fri Aug 13 2021 23:10:44",
            "keyStrokeInfo": "g",
            "position": "9,3"
        },
        {
            "operation": "TYPED",
            "lines": 0,
            "keyStrokeTimeStamp": "Fri Aug 13 2021 23:10:44",
            "keyStrokeInfo": "g",
            "position": "9,4"
        },
        {
            "operation": "TYPED",
            "lines": 0,
            "keyStrokeTimeStamp": "Fri Aug 13 2021 23:10:44",
            "keyStrokeInfo": "s",
            "position": "9,5"
        },
        {
            "operation": "TYPED",
            "lines": 0,
            "keyStrokeTimeStamp": "Fri Aug 13 2021 23:10:44",
            "keyStrokeInfo": " ",
            "position": "9,6"
        },
        {
            "operation": "TYPED",
            "lines": 0,
            "keyStrokeTimeStamp": "Fri Aug 13 2021 23:10:45",
            "keyStrokeInfo": "=",
            "position": "9,7"
        },
        {
            "operation": "TYPED",
            "lines": 0,
            "keyStrokeTimeStamp": "Fri Aug 13 2021 23:10:45",
            "keyStrokeInfo": " ",
            "position": "9,8"
        },
        {
            "operation": "TYPED",
            "lines": 0,
            "keyStrokeTimeStamp": "Fri Aug 13 2021 23:10:46",
            "keyStrokeInfo": "a",
            "position": "9,9"
        },
        {
            "operation": "TYPED",
            "lines": 0,
            "keyStrokeTimeStamp": "Fri Aug 13 2021 23:10:46",
            "keyStrokeInfo": "b",
            "position": "9,10"
        },
        {
            "operation": "TYPED",
            "lines": 0,
            "keyStrokeTimeStamp": "Fri Aug 13 2021 23:10:46",
            "keyStrokeInfo": "s",
            "position": "9,11"
        },
        {
            "operation": "TYPED",
            "lines": 0,
            "keyStrokeTimeStamp": "Fri Aug 13 2021 23:10:47",
            "keyStrokeInfo": "()",
            "position": "9,12"
        },
        {
            "operation": "TYPED",
            "lines": 0,
            "keyStrokeTimeStamp": "Fri Aug 13 2021 23:10:47",
            "keyStrokeInfo": "e",
            "position": "9,13"
        },
        {
            "operation": "TYPED",
            "lines": 0,
            "keyStrokeTimeStamp": "Fri Aug 13 2021 23:10:47",
            "keyStrokeInfo": "g",
            "position": "9,14"
        },
        {
            "operation": "TYPED",
            "lines": 0,
            "keyStrokeTimeStamp": "Fri Aug 13 2021 23:10:47",
            "keyStrokeInfo": "g",
            "position": "9,15"
        },
        {
            "operation": "TYPED",
            "lines": 0,
            "keyStrokeTimeStamp": "Fri Aug 13 2021 23:10:48",
            "keyStrokeInfo": "s",
            "position": "9,16"
        },
        {
            "operation": "TYPED",
            "lines": 0,
            "keyStrokeTimeStamp": "Fri Aug 13 2021 23:10:48",
            "keyStrokeInfo": "eggs",
            "position": "9,13"
        },
        {
            "operation": "TYPED",
            "lines": 0,
            "keyStrokeTimeStamp": "Fri Aug 13 2021 23:10:50",
            "keyStrokeInfo": "\r\n\t",
            "position": "9,18"
        },
        {
            "operation": "TYPED",
            "lines": 0,
            "keyStrokeTimeStamp": "Fri Aug 13 2021 23:11:11",
            "keyStrokeInfo": "i",
            "position": "10,2"
        },
        {
            "operation": "TYPED",
            "lines": 0,
            "keyStrokeTimeStamp": "Fri Aug 13 2021 23:11:11",
            "keyStrokeInfo": "f",
            "position": "10,3"
        },
        {
            "operation": "TYPED",
            "lines": 0,
            "keyStrokeTimeStamp": "Fri Aug 13 2021 23:11:12",
            "keyStrokeInfo": "()",
            "position": "10,4"
        },
        {
            "operation": "TYPED",
            "lines": 0,
            "keyStrokeTimeStamp": "Fri Aug 13 2021 23:11:12",
            "keyStrokeInfo": "a",
            "position": "10,5"
        },
        {
            "operation": "DELETE",
            "lines": 0,
            "keyStrokeTimeStamp": "Fri Aug 13 2021 23:11:12",
            "keyStrokeInfo": "",
            "position": "10,5"
        },
        {
            "operation": "TYPED",
            "lines": 0,
            "keyStrokeTimeStamp": "Fri Aug 13 2021 23:11:12",
            "keyStrokeInfo": "e",
            "position": "10,5"
        },
        {
            "operation": "TYPED",
            "lines": 0,
            "keyStrokeTimeStamp": "Fri Aug 13 2021 23:11:13",
            "keyStrokeInfo": "g",
            "position": "10,6"
        },
        {
            "operation": "TYPED",
            "lines": 0,
            "keyStrokeTimeStamp": "Fri Aug 13 2021 23:11:13",
            "keyStrokeInfo": "g",
            "position": "10,7"
        },
        {
            "operation": "TYPED",
            "lines": 0,
            "keyStrokeTimeStamp": "Fri Aug 13 2021 23:11:14",
            "keyStrokeInfo": "s",
            "position": "10,8"
        },
        {
            "operation": "TYPED",
            "lines": 0,
            "keyStrokeTimeStamp": "Fri Aug 13 2021 23:11:14",
            "keyStrokeInfo": ">",
            "position": "10,9"
        },
        {
            "operation": "TYPED",
            "lines": 0,
            "keyStrokeTimeStamp": "Fri Aug 13 2021 23:11:15",
            "keyStrokeInfo": "1",
            "position": "10,10"
        },
        {
            "operation": "DELETE",
            "lines": 0,
            "keyStrokeTimeStamp": "Fri Aug 13 2021 23:11:16",
            "keyStrokeInfo": "",
            "position": "10,10"
        },
        {
            "operation": "TYPED",
            "lines": 0,
            "keyStrokeTimeStamp": "Fri Aug 13 2021 23:11:18",
            "keyStrokeInfo": "0",
            "position": "10,10"
        },
        {
            "operation": "TYPED",
            "lines": 0,
            "keyStrokeTimeStamp": "Fri Aug 13 2021 23:11:18",
            "keyStrokeInfo": " ",
            "position": "10,11"
        },
        {
            "operation": "TYPED",
            "lines": 0,
            "keyStrokeTimeStamp": "Fri Aug 13 2021 23:11:18",
            "keyStrokeInfo": "a",
            "position": "10,12"
        },
        {
            "operation": "TYPED",
            "lines": 0,
            "keyStrokeTimeStamp": "Fri Aug 13 2021 23:11:18",
            "keyStrokeInfo": "n",
            "position": "10,13"
        },
        {
            "operation": "TYPED",
            "lines": 0,
            "keyStrokeTimeStamp": "Fri Aug 13 2021 23:11:19",
            "keyStrokeInfo": "d",
            "position": "10,14"
        },
        {
            "operation": "TYPED",
            "lines": 0,
            "keyStrokeTimeStamp": "Fri Aug 13 2021 23:11:19",
            "keyStrokeInfo": " ",
            "position": "10,15"
        },
        {
            "operation": "TYPED",
            "lines": 0,
            "keyStrokeTimeStamp": "Fri Aug 13 2021 23:11:20",
            "keyStrokeInfo": "e",
            "position": "10,16"
        },
        {
            "operation": "TYPED",
            "lines": 0,
            "keyStrokeTimeStamp": "Fri Aug 13 2021 23:11:20",
            "keyStrokeInfo": "g",
            "position": "10,17"
        },
        {
            "operation": "TYPED",
            "lines": 0,
            "keyStrokeTimeStamp": "Fri Aug 13 2021 23:11:20",
            "keyStrokeInfo": "g",
            "position": "10,18"
        },
        {
            "operation": "TYPED",
            "lines": 0,
            "keyStrokeTimeStamp": "Fri Aug 13 2021 23:11:20",
            "keyStrokeInfo": "s",
            "position": "10,19"
        },
        {
            "operation": "TYPED",
            "lines": 0,
            "keyStrokeTimeStamp": "Fri Aug 13 2021 23:11:21",
            "keyStrokeInfo": "<",
            "position": "10,20"
        },
        {
            "operation": "TYPED",
            "lines": 0,
            "keyStrokeTimeStamp": "Fri Aug 13 2021 23:11:23",
            "keyStrokeInfo": "=",
            "position": "10,21"
        },
        {
            "operation": "TYPED",
            "lines": 0,
            "keyStrokeTimeStamp": "Fri Aug 13 2021 23:11:23",
            "keyStrokeInfo": "1",
            "position": "10,22"
        },
        {
            "operation": "TYPED",
            "lines": 0,
            "keyStrokeTimeStamp": "Fri Aug 13 2021 23:11:24",
            "keyStrokeInfo": "2",
            "position": "10,23"
        },
        {
            "operation": "TYPED",
            "lines": 0,
            "keyStrokeTimeStamp": "Fri Aug 13 2021 23:11:25",
            "keyStrokeInfo": ":",
            "position": "10,25"
        },
        {
            "operation": "TYPED",
            "lines": 0,
            "keyStrokeTimeStamp": "Fri Aug 13 2021 23:11:25",
            "keyStrokeInfo": "\r\n\t\t",
            "position": "10,26"
        },
        {
            "operation": "DELETE",
            "lines": 0,
            "keyStrokeTimeStamp": "Fri Aug 13 2021 23:11:30",
            "keyStrokeInfo": "\r\n\t",
            "position": "8,23"
        },
        {
            "operation": "TYPED",
            "lines": 0,
            "keyStrokeTimeStamp": "Fri Aug 13 2021 23:11:30",
            "keyStrokeInfo": "c",
            "position": "9,2"
        },
        {
            "operation": "TYPED",
            "lines": 0,
            "keyStrokeTimeStamp": "Fri Aug 13 2021 23:11:31",
            "keyStrokeInfo": "o",
            "position": "9,3"
        },
        {
            "operation": "TYPED",
            "lines": 0,
            "keyStrokeTimeStamp": "Fri Aug 13 2021 23:11:31",
            "keyStrokeInfo": "u",
            "position": "9,4"
        },
        {
            "operation": "TYPED",
            "lines": 0,
            "keyStrokeTimeStamp": "Fri Aug 13 2021 23:11:31",
            "keyStrokeInfo": "n",
            "position": "9,5"
        },
        {
            "operation": "TYPED",
            "lines": 0,
            "keyStrokeTimeStamp": "Fri Aug 13 2021 23:11:32",
            "keyStrokeInfo": "=",
            "position": "9,6"
        },
        {
            "operation": "TYPED",
            "lines": 0,
            "keyStrokeTimeStamp": "Fri Aug 13 2021 23:11:32",
            "keyStrokeInfo": "0",
            "position": "9,7"
        },
        {
            "operation": "DELETE",
            "lines": 0,
            "keyStrokeTimeStamp": "Fri Aug 13 2021 23:11:33",
            "keyStrokeInfo": "",
            "position": "9,7"
        },
        {
            "operation": "DELETE",
            "lines": 0,
            "keyStrokeTimeStamp": "Fri Aug 13 2021 23:11:33",
            "keyStrokeInfo": "",
            "position": "9,6"
        },
        {
            "operation": "TYPED",
            "lines": 0,
            "keyStrokeTimeStamp": "Fri Aug 13 2021 23:11:34",
            "keyStrokeInfo": "t",
            "position": "9,6"
        },
        {
            "operation": "TYPED",
            "lines": 0,
            "keyStrokeTimeStamp": "Fri Aug 13 2021 23:11:34",
            "keyStrokeInfo": "=",
            "position": "9,7"
        },
        {
            "operation": "TYPED",
            "lines": 0,
            "keyStrokeTimeStamp": "Fri Aug 13 2021 23:11:34",
            "keyStrokeInfo": "0",
            "position": "9,8"
        },
        {
            "operation": "DELETE",
            "lines": 0,
            "keyStrokeTimeStamp": "Fri Aug 13 2021 23:11:37",
            "keyStrokeInfo": "",
            "position": "9,8"
        },
        {
            "operation": "DELETE",
            "lines": 0,
            "keyStrokeTimeStamp": "Fri Aug 13 2021 23:11:37",
            "keyStrokeInfo": "",
            "position": "9,7"
        },
        {
            "operation": "DELETE",
            "lines": 0,
            "keyStrokeTimeStamp": "Fri Aug 13 2021 23:11:37",
            "keyStrokeInfo": "",
            "position": "9,6"
        },
        {
            "operation": "DELETE",
            "lines": 0,
            "keyStrokeTimeStamp": "Fri Aug 13 2021 23:11:37",
            "keyStrokeInfo": "",
            "position": "9,5"
        },
        {
            "operation": "DELETE",
            "lines": 0,
            "keyStrokeTimeStamp": "Fri Aug 13 2021 23:11:38",
            "keyStrokeInfo": "",
            "position": "9,4"
        },
        {
            "operation": "DELETE",
            "lines": 0,
            "keyStrokeTimeStamp": "Fri Aug 13 2021 23:11:38",
            "keyStrokeInfo": "",
            "position": "9,3"
        },
        {
            "operation": "DELETE",
            "lines": 0,
            "keyStrokeTimeStamp": "Fri Aug 13 2021 23:11:38",
            "keyStrokeInfo": "",
            "position": "9,2"
        },
        {
            "operation": "DELETE",
            "lines": 0,
            "keyStrokeTimeStamp": "Fri Aug 13 2021 23:11:38",
            "keyStrokeInfo": "",
            "position": "9,1"
        },
        {
            "operation": "DELETE",
            "lines": 1,
            "keyStrokeTimeStamp": "Fri Aug 13 2021 23:11:39",
            "keyStrokeInfo": "",
            "position": "8,23"
        },
        {
            "operation": "DELETE",
            "lines": 1,
            "keyStrokeTimeStamp": "Fri Aug 13 2021 23:11:41",
            "keyStrokeInfo": "",
            "position": "10,26"
        },
        {
            "operation": "TYPED",
            "lines": 0,
            "keyStrokeTimeStamp": "Fri Aug 13 2021 23:11:41",
            "keyStrokeInfo": "\r\n\t\t",
            "position": "10,26"
        },
        {
            "operation": "TYPED",
            "lines": 0,
            "keyStrokeTimeStamp": "Fri Aug 13 2021 23:11:42",
            "keyStrokeInfo": "r",
            "position": "11,3"
        },
        {
            "operation": "TYPED",
            "lines": 0,
            "keyStrokeTimeStamp": "Fri Aug 13 2021 23:11:42",
            "keyStrokeInfo": "e",
            "position": "11,4"
        },
        {
            "operation": "TYPED",
            "lines": 0,
            "keyStrokeTimeStamp": "Fri Aug 13 2021 23:11:42",
            "keyStrokeInfo": "t",
            "position": "11,5"
        },
        {
            "operation": "TYPED",
            "lines": 0,
            "keyStrokeTimeStamp": "Fri Aug 13 2021 23:11:43",
            "keyStrokeInfo": "u",
            "position": "11,6"
        },
        {
            "operation": "TYPED",
            "lines": 0,
            "keyStrokeTimeStamp": "Fri Aug 13 2021 23:11:43",
            "keyStrokeInfo": "r",
            "position": "11,7"
        },
        {
            "operation": "TYPED",
            "lines": 0,
            "keyStrokeTimeStamp": "Fri Aug 13 2021 23:11:43",
            "keyStrokeInfo": "n",
            "position": "11,8"
        },
        {
            "operation": "TYPED",
            "lines": 0,
            "keyStrokeTimeStamp": "Fri Aug 13 2021 23:11:44",
            "keyStrokeInfo": "()",
            "position": "11,9"
        },
        {
            "operation": "TYPED",
            "lines": 0,
            "keyStrokeTimeStamp": "Fri Aug 13 2021 23:11:44",
            "keyStrokeInfo": "1",
            "position": "11,10"
        },
        {
            "operation": "TYPED",
            "lines": 0,
            "keyStrokeTimeStamp": "Fri Aug 13 2021 23:11:45",
            "keyStrokeInfo": "\r\n\t\t",
            "position": "11,12"
        },
        {
            "operation": "DELETE",
            "lines": 0,
            "keyStrokeTimeStamp": "Fri Aug 13 2021 23:11:45",
            "keyStrokeInfo": "",
            "position": "12,2"
        },
        {
            "operation": "TYPED",
            "lines": 0,
            "keyStrokeTimeStamp": "Fri Aug 13 2021 23:11:46",
            "keyStrokeInfo": "i",
            "position": "12,2"
        },
        {
            "operation": "TYPED",
            "lines": 0,
            "keyStrokeTimeStamp": "Fri Aug 13 2021 23:11:46",
            "keyStrokeInfo": "f",
            "position": "12,3"
        },
        {
            "operation": "TYPED",
            "lines": 0,
            "keyStrokeTimeStamp": "Fri Aug 13 2021 23:11:46",
            "keyStrokeInfo": "()",
            "position": "12,4"
        },
        {
            "operation": "TYPED",
            "lines": 0,
            "keyStrokeTimeStamp": "Fri Aug 13 2021 23:11:48",
            "keyStrokeInfo": "e",
            "position": "12,5"
        },
        {
            "operation": "TYPED",
            "lines": 0,
            "keyStrokeTimeStamp": "Fri Aug 13 2021 23:11:49",
            "keyStrokeInfo": "g",
            "position": "12,6"
        },
        {
            "operation": "TYPED",
            "lines": 0,
            "keyStrokeTimeStamp": "Fri Aug 13 2021 23:11:49",
            "keyStrokeInfo": "g",
            "position": "12,7"
        },
        {
            "operation": "TYPED",
            "lines": 0,
            "keyStrokeTimeStamp": "Fri Aug 13 2021 23:11:49",
            "keyStrokeInfo": "s",
            "position": "12,8"
        },
        {
            "operation": "TYPED",
            "lines": 0,
            "keyStrokeTimeStamp": "Fri Aug 13 2021 23:11:50",
            "keyStrokeInfo": ">",
            "position": "12,9"
        },
        {
            "operation": "TYPED",
            "lines": 0,
            "keyStrokeTimeStamp": "Fri Aug 13 2021 23:11:50",
            "keyStrokeInfo": "1",
            "position": "12,10"
        },
        {
            "operation": "TYPED",
            "lines": 0,
            "keyStrokeTimeStamp": "Fri Aug 13 2021 23:11:50",
            "keyStrokeInfo": "2",
            "position": "12,11"
        },
        {
            "operation": "TYPED",
            "lines": 0,
            "keyStrokeTimeStamp": "Fri Aug 13 2021 23:11:51",
            "keyStrokeInfo": " ",
            "position": "12,12"
        },
        {
            "operation": "TYPED",
            "lines": 0,
            "keyStrokeTimeStamp": "Fri Aug 13 2021 23:11:51",
            "keyStrokeInfo": "a",
            "position": "12,13"
        },
        {
            "operation": "TYPED",
            "lines": 0,
            "keyStrokeTimeStamp": "Fri Aug 13 2021 23:11:51",
            "keyStrokeInfo": "n",
            "position": "12,14"
        },
        {
            "operation": "TYPED",
            "lines": 0,
            "keyStrokeTimeStamp": "Fri Aug 13 2021 23:11:51",
            "keyStrokeInfo": "d",
            "position": "12,15"
        },
        {
            "operation": "TYPED",
            "lines": 0,
            "keyStrokeTimeStamp": "Fri Aug 13 2021 23:11:51",
            "keyStrokeInfo": " ",
            "position": "12,16"
        },
        {
            "operation": "TYPED",
            "lines": 0,
            "keyStrokeTimeStamp": "Fri Aug 13 2021 23:11:52",
            "keyStrokeInfo": "e",
            "position": "12,17"
        },
        {
            "operation": "TYPED",
            "lines": 0,
            "keyStrokeTimeStamp": "Fri Aug 13 2021 23:11:52",
            "keyStrokeInfo": "g",
            "position": "12,18"
        },
        {
            "operation": "TYPED",
            "lines": 0,
            "keyStrokeTimeStamp": "Fri Aug 13 2021 23:11:52",
            "keyStrokeInfo": "g",
            "position": "12,19"
        },
        {
            "operation": "TYPED",
            "lines": 0,
            "keyStrokeTimeStamp": "Fri Aug 13 2021 23:11:53",
            "keyStrokeInfo": "s",
            "position": "12,20"
        },
        {
            "operation": "TYPED",
            "lines": 0,
            "keyStrokeTimeStamp": "Fri Aug 13 2021 23:11:53",
            "keyStrokeInfo": "<",
            "position": "12,21"
        },
        {
            "operation": "TYPED",
            "lines": 0,
            "keyStrokeTimeStamp": "Fri Aug 13 2021 23:11:54",
            "keyStrokeInfo": "=",
            "position": "12,22"
        },
        {
            "operation": "TYPED",
            "lines": 0,
            "keyStrokeTimeStamp": "Fri Aug 13 2021 23:11:55",
            "keyStrokeInfo": "2",
            "position": "12,23"
        },
        {
            "operation": "TYPED",
            "lines": 0,
            "keyStrokeTimeStamp": "Fri Aug 13 2021 23:11:55",
            "keyStrokeInfo": "4",
            "position": "12,24"
        },
        {
            "operation": "TYPED",
            "lines": 0,
            "keyStrokeTimeStamp": "Fri Aug 13 2021 23:11:57",
            "keyStrokeInfo": ":",
            "position": "12,26"
        },
        {
            "operation": "TYPED",
            "lines": 0,
            "keyStrokeTimeStamp": "Fri Aug 13 2021 23:11:57",
            "keyStrokeInfo": "\r\n\t\t",
            "position": "12,27"
        },
        {
            "operation": "TYPED",
            "lines": 0,
            "keyStrokeTimeStamp": "Fri Aug 13 2021 23:11:58",
            "keyStrokeInfo": "r",
            "position": "13,3"
        },
        {
            "operation": "TYPED",
            "lines": 0,
            "keyStrokeTimeStamp": "Fri Aug 13 2021 23:11:58",
            "keyStrokeInfo": "e",
            "position": "13,4"
        },
        {
            "operation": "TYPED",
            "lines": 0,
            "keyStrokeTimeStamp": "Fri Aug 13 2021 23:11:58",
            "keyStrokeInfo": "t",
            "position": "13,5"
        },
        {
            "operation": "TYPED",
            "lines": 0,
            "keyStrokeTimeStamp": "Fri Aug 13 2021 23:11:58",
            "keyStrokeInfo": "u",
            "position": "13,6"
        },
        {
            "operation": "TYPED",
            "lines": 0,
            "keyStrokeTimeStamp": "Fri Aug 13 2021 23:11:58",
            "keyStrokeInfo": "r",
            "position": "13,7"
        },
        {
            "operation": "TYPED",
            "lines": 0,
            "keyStrokeTimeStamp": "Fri Aug 13 2021 23:11:58",
            "keyStrokeInfo": "n",
            "position": "13,8"
        },
        {
            "operation": "TYPED",
            "lines": 0,
            "keyStrokeTimeStamp": "Fri Aug 13 2021 23:11:59",
            "keyStrokeInfo": "()",
            "position": "13,9"
        },
        {
            "operation": "TYPED",
            "lines": 0,
            "keyStrokeTimeStamp": "Fri Aug 13 2021 23:11:59",
            "keyStrokeInfo": "2",
            "position": "13,10"
        },
        {
            "operation": "TYPED",
            "lines": 0,
            "keyStrokeTimeStamp": "Fri Aug 13 2021 23:12:00",
            "keyStrokeInfo": "\r\n\t\t",
            "position": "13,12"
        },
        {
            "operation": "DELETE",
            "lines": 0,
            "keyStrokeTimeStamp": "Fri Aug 13 2021 23:12:01",
            "keyStrokeInfo": "",
            "position": "14,2"
        },
        {
            "operation": "TYPED",
            "lines": 0,
            "keyStrokeTimeStamp": "Fri Aug 13 2021 23:12:02",
            "keyStrokeInfo": "i",
            "position": "14,2"
        },
        {
            "operation": "TYPED",
            "lines": 0,
            "keyStrokeTimeStamp": "Fri Aug 13 2021 23:12:02",
            "keyStrokeInfo": "f",
            "position": "14,3"
        },
        {
            "operation": "TYPED",
            "lines": 0,
            "keyStrokeTimeStamp": "Fri Aug 13 2021 23:12:02",
            "keyStrokeInfo": "()",
            "position": "14,4"
        },
        {
            "operation": "TYPED",
            "lines": 0,
            "keyStrokeTimeStamp": "Fri Aug 13 2021 23:12:03",
            "keyStrokeInfo": "e",
            "position": "14,5"
        },
        {
            "operation": "TYPED",
            "lines": 0,
            "keyStrokeTimeStamp": "Fri Aug 13 2021 23:12:03",
            "keyStrokeInfo": "g",
            "position": "14,6"
        },
        {
            "operation": "TYPED",
            "lines": 0,
            "keyStrokeTimeStamp": "Fri Aug 13 2021 23:12:03",
            "keyStrokeInfo": "g",
            "position": "14,7"
        },
        {
            "operation": "TYPED",
            "lines": 0,
            "keyStrokeTimeStamp": "Fri Aug 13 2021 23:12:04",
            "keyStrokeInfo": "s",
            "position": "14,8"
        },
        {
            "operation": "TYPED",
            "lines": 0,
            "keyStrokeTimeStamp": "Fri Aug 13 2021 23:12:05",
            "keyStrokeInfo": ">",
            "position": "14,9"
        },
        {
            "operation": "TYPED",
            "lines": 0,
            "keyStrokeTimeStamp": "Fri Aug 13 2021 23:12:05",
            "keyStrokeInfo": "2",
            "position": "14,10"
        },
        {
            "operation": "TYPED",
            "lines": 0,
            "keyStrokeTimeStamp": "Fri Aug 13 2021 23:12:06",
            "keyStrokeInfo": "4",
            "position": "14,11"
        },
        {
            "operation": "TYPED",
            "lines": 0,
            "keyStrokeTimeStamp": "Fri Aug 13 2021 23:12:06",
            "keyStrokeInfo": " ",
            "position": "14,12"
        },
        {
            "operation": "TYPED",
            "lines": 0,
            "keyStrokeTimeStamp": "Fri Aug 13 2021 23:12:06",
            "keyStrokeInfo": "a",
            "position": "14,13"
        },
        {
            "operation": "TYPED",
            "lines": 0,
            "keyStrokeTimeStamp": "Fri Aug 13 2021 23:12:06",
            "keyStrokeInfo": "n",
            "position": "14,14"
        },
        {
            "operation": "TYPED",
            "lines": 0,
            "keyStrokeTimeStamp": "Fri Aug 13 2021 23:12:06",
            "keyStrokeInfo": "d",
            "position": "14,15"
        },
        {
            "operation": "TYPED",
            "lines": 0,
            "keyStrokeTimeStamp": "Fri Aug 13 2021 23:12:06",
            "keyStrokeInfo": " ",
            "position": "14,16"
        },
        {
            "operation": "TYPED",
            "lines": 0,
            "keyStrokeTimeStamp": "Fri Aug 13 2021 23:12:07",
            "keyStrokeInfo": "e",
            "position": "14,17"
        },
        {
            "operation": "TYPED",
            "lines": 0,
            "keyStrokeTimeStamp": "Fri Aug 13 2021 23:12:07",
            "keyStrokeInfo": "g",
            "position": "14,18"
        },
        {
            "operation": "TYPED",
            "lines": 0,
            "keyStrokeTimeStamp": "Fri Aug 13 2021 23:12:08",
            "keyStrokeInfo": "g",
            "position": "14,19"
        },
        {
            "operation": "TYPED",
            "lines": 0,
            "keyStrokeTimeStamp": "Fri Aug 13 2021 23:12:08",
            "keyStrokeInfo": "s",
            "position": "14,20"
        },
        {
            "operation": "TYPED",
            "lines": 0,
            "keyStrokeTimeStamp": "Fri Aug 13 2021 23:12:09",
            "keyStrokeInfo": "<",
            "position": "14,21"
        },
        {
            "operation": "TYPED",
            "lines": 0,
            "keyStrokeTimeStamp": "Fri Aug 13 2021 23:12:09",
            "keyStrokeInfo": "=",
            "position": "14,22"
        },
        {
            "operation": "TYPED",
            "lines": 0,
            "keyStrokeTimeStamp": "Fri Aug 13 2021 23:12:12",
            "keyStrokeInfo": "3",
            "position": "14,23"
        },
        {
            "operation": "TYPED",
            "lines": 0,
            "keyStrokeTimeStamp": "Fri Aug 13 2021 23:12:12",
            "keyStrokeInfo": "6",
            "position": "14,24"
        },
        {
            "operation": "TYPED",
            "lines": 0,
            "keyStrokeTimeStamp": "Fri Aug 13 2021 23:12:14",
            "keyStrokeInfo": ":",
            "position": "14,26"
        },
        {
            "operation": "TYPED",
            "lines": 0,
            "keyStrokeTimeStamp": "Fri Aug 13 2021 23:12:15",
            "keyStrokeInfo": "\r\n\t\t",
            "position": "14,27"
        },
        {
            "operation": "TYPED",
            "lines": 0,
            "keyStrokeTimeStamp": "Fri Aug 13 2021 23:12:15",
            "keyStrokeInfo": "r",
            "position": "15,3"
        },
        {
            "operation": "TYPED",
            "lines": 0,
            "keyStrokeTimeStamp": "Fri Aug 13 2021 23:12:15",
            "keyStrokeInfo": "e",
            "position": "15,4"
        },
        {
            "operation": "TYPED",
            "lines": 0,
            "keyStrokeTimeStamp": "Fri Aug 13 2021 23:12:16",
            "keyStrokeInfo": "t",
            "position": "15,5"
        },
        {
            "operation": "TYPED",
            "lines": 0,
            "keyStrokeTimeStamp": "Fri Aug 13 2021 23:12:16",
            "keyStrokeInfo": "u",
            "position": "15,6"
        },
        {
            "operation": "TYPED",
            "lines": 0,
            "keyStrokeTimeStamp": "Fri Aug 13 2021 23:12:16",
            "keyStrokeInfo": "r",
            "position": "15,7"
        },
        {
            "operation": "TYPED",
            "lines": 0,
            "keyStrokeTimeStamp": "Fri Aug 13 2021 23:12:16",
            "keyStrokeInfo": "n",
            "position": "15,8"
        },
        {
            "operation": "TYPED",
            "lines": 0,
            "keyStrokeTimeStamp": "Fri Aug 13 2021 23:12:17",
            "keyStrokeInfo": "()",
            "position": "15,9"
        },
        {
            "operation": "TYPED",
            "lines": 0,
            "keyStrokeTimeStamp": "Fri Aug 13 2021 23:12:17",
            "keyStrokeInfo": "1",
            "position": "15,10"
        },
        {
            "operation": "TYPED",
            "lines": 0,
            "keyStrokeTimeStamp": "Fri Aug 13 2021 23:12:17",
            "keyStrokeInfo": "2",
            "position": "15,11"
        },
        {
            "operation": "DELETE",
            "lines": 0,
            "keyStrokeTimeStamp": "Fri Aug 13 2021 23:12:18",
            "keyStrokeInfo": "",
            "position": "15,11"
        },
        {
            "operation": "DELETE",
            "lines": 0,
            "keyStrokeTimeStamp": "Fri Aug 13 2021 23:12:19",
            "keyStrokeInfo": "",
            "position": "15,10"
        },
        {
            "operation": "TYPED",
            "lines": 0,
            "keyStrokeTimeStamp": "Fri Aug 13 2021 23:12:20",
            "keyStrokeInfo": "3",
            "position": "15,10"
        },
        {
            "operation": "TYPED",
            "lines": 0,
            "keyStrokeTimeStamp": "Fri Aug 13 2021 23:12:35",
            "keyStrokeInfo": "\r\n\t",
            "position": "9,18"
        },
        {
            "operation": "TYPED",
            "lines": 0,
            "keyStrokeTimeStamp": "Fri Aug 13 2021 23:12:35",
            "keyStrokeInfo": "i",
            "position": "10,2"
        },
        {
            "operation": "TYPED",
            "lines": 0,
            "keyStrokeTimeStamp": "Fri Aug 13 2021 23:12:36",
            "keyStrokeInfo": "f",
            "position": "10,3"
        },
        {
            "operation": "TYPED",
            "lines": 0,
            "keyStrokeTimeStamp": "Fri Aug 13 2021 23:12:36",
            "keyStrokeInfo": "()",
            "position": "10,4"
        },
        {
            "operation": "TYPED",
            "lines": 0,
            "keyStrokeTimeStamp": "Fri Aug 13 2021 23:12:36",
            "keyStrokeInfo": "e",
            "position": "10,5"
        },
        {
            "operation": "TYPED",
            "lines": 0,
            "keyStrokeTimeStamp": "Fri Aug 13 2021 23:12:37",
            "keyStrokeInfo": "g",
            "position": "10,6"
        },
        {
            "operation": "TYPED",
            "lines": 0,
            "keyStrokeTimeStamp": "Fri Aug 13 2021 23:12:37",
            "keyStrokeInfo": "g",
            "position": "10,7"
        },
        {
            "operation": "TYPED",
            "lines": 0,
            "keyStrokeTimeStamp": "Fri Aug 13 2021 23:12:37",
            "keyStrokeInfo": "s",
            "position": "10,8"
        },
        {
            "operation": "TYPED",
            "lines": 0,
            "keyStrokeTimeStamp": "Fri Aug 13 2021 23:12:38",
            "keyStrokeInfo": "=",
            "position": "10,9"
        },
        {
            "operation": "TYPED",
            "lines": 0,
            "keyStrokeTimeStamp": "Fri Aug 13 2021 23:12:38",
            "keyStrokeInfo": "=",
            "position": "10,10"
        },
        {
            "operation": "TYPED",
            "lines": 0,
            "keyStrokeTimeStamp": "Fri Aug 13 2021 23:12:38",
            "keyStrokeInfo": "0",
            "position": "10,11"
        },
        {
            "operation": "TYPED",
            "lines": 0,
            "keyStrokeTimeStamp": "Fri Aug 13 2021 23:12:40",
            "keyStrokeInfo": ":",
            "position": "10,13"
        },
        {
            "operation": "TYPED",
            "lines": 0,
            "keyStrokeTimeStamp": "Fri Aug 13 2021 23:12:40",
            "keyStrokeInfo": "\r\n\t\t",
            "position": "10,14"
        },
        {
            "operation": "TYPED",
            "lines": 0,
            "keyStrokeTimeStamp": "Fri Aug 13 2021 23:12:40",
            "keyStrokeInfo": "r",
            "position": "11,3"
        },
        {
            "operation": "TYPED",
            "lines": 0,
            "keyStrokeTimeStamp": "Fri Aug 13 2021 23:12:40",
            "keyStrokeInfo": "e",
            "position": "11,4"
        },
        {
            "operation": "TYPED",
            "lines": 0,
            "keyStrokeTimeStamp": "Fri Aug 13 2021 23:12:41",
            "keyStrokeInfo": "t",
            "position": "11,5"
        },
        {
            "operation": "TYPED",
            "lines": 0,
            "keyStrokeTimeStamp": "Fri Aug 13 2021 23:12:41",
            "keyStrokeInfo": "u",
            "position": "11,6"
        },
        {
            "operation": "TYPED",
            "lines": 0,
            "keyStrokeTimeStamp": "Fri Aug 13 2021 23:12:41",
            "keyStrokeInfo": "r",
            "position": "11,7"
        },
        {
            "operation": "TYPED",
            "lines": 0,
            "keyStrokeTimeStamp": "Fri Aug 13 2021 23:12:41",
            "keyStrokeInfo": "n",
            "position": "11,8"
        },
        {
            "operation": "TYPED",
            "lines": 0,
            "keyStrokeTimeStamp": "Fri Aug 13 2021 23:12:42",
            "keyStrokeInfo": "()",
            "position": "11,9"
        },
        {
            "operation": "TYPED",
            "lines": 0,
            "keyStrokeTimeStamp": "Fri Aug 13 2021 23:12:42",
            "keyStrokeInfo": "0",
            "position": "11,10"
        },
        {
            "operation": "TYPED",
            "lines": 0,
            "keyStrokeTimeStamp": "Fri Aug 13 2021 23:12:45",
            "keyStrokeInfo": "e",
            "position": "12,2"
        },
        {
            "operation": "TYPED",
            "lines": 0,
            "keyStrokeTimeStamp": "Fri Aug 13 2021 23:12:45",
            "keyStrokeInfo": "l",
            "position": "12,3"
        },
        {
            "operation": "TYPED",
            "lines": 0,
            "keyStrokeTimeStamp": "Fri Aug 13 2021 23:12:47",
            "keyStrokeInfo": "e",
            "position": "14,2"
        },
        {
            "operation": "TYPED",
            "lines": 0,
            "keyStrokeTimeStamp": "Fri Aug 13 2021 23:12:48",
            "keyStrokeInfo": "l",
            "position": "14,3"
        },
        {
            "operation": "TYPED",
            "lines": 0,
            "keyStrokeTimeStamp": "Fri Aug 13 2021 23:12:48",
            "keyStrokeInfo": "i",
            "position": "14,4"
        },
        {
            "operation": "DELETE",
            "lines": 0,
            "keyStrokeTimeStamp": "Fri Aug 13 2021 23:12:49",
            "keyStrokeInfo": "",
            "position": "14,4"
        },
        {
            "operation": "TYPED",
            "lines": 0,
            "keyStrokeTimeStamp": "Fri Aug 13 2021 23:12:54",
            "keyStrokeInfo": "e",
            "position": "16,2"
        },
        {
            "operation": "TYPED",
            "lines": 0,
            "keyStrokeTimeStamp": "Fri Aug 13 2021 23:12:54",
            "keyStrokeInfo": "l",
            "position": "16,3"
        }
    ]
}